configurate/__init__.py
configurate/version.py
configurate/_version.py
configurate-0.4.1.dist-info/RECORD
configurate-0.4.1.dist-info/WHEEL
configurate-0.4.1.dist-info/METADATA
configurate-0.4.1.dist-info/top_level.txt
configurate-0.4.1.dist-info/metadata.json
configurate-0.4.1.dist-info/DESCRIPTION.rst
