Metadata-Version: 2.0
Name: configurate
Version: 0.4.1
Summary: A simple, but smart, dict-like configuration object that's not opinionated about the file format you prefer.
Home-page: https://github.com/mikenerone/configurate
Author: Mike Nerone
Author-email: mike@nerone.org
License: ALv2
Keywords: configuration,configurate,config,dict,attribute
Platform: UNKNOWN
Classifier: Development Status :: 4 - Beta
Classifier: Intended Audience :: Developers
Classifier: Natural Language :: English
Classifier: License :: OSI Approved :: Apache Software License
Classifier: Operating System :: OS Independent
Classifier: Programming Language :: Python
Classifier: Programming Language :: Python :: 2.7
Classifier: Programming Language :: Python :: 3
Classifier: Programming Language :: Python :: 3.1
Classifier: Programming Language :: Python :: 3.2
Classifier: Programming Language :: Python :: 3.3
Classifier: Programming Language :: Python :: 3.4
